setup.py
distributions_package_oop/Binomialdistribution.py
distributions_package_oop/Gaussiandistribution.py
distributions_package_oop/Generaldistribution.py
distributions_package_oop/__init__.py
distributions_package_oop.egg-info/PKG-INFO
distributions_package_oop.egg-info/SOURCES.txt
distributions_package_oop.egg-info/dependency_links.txt
distributions_package_oop.egg-info/not-zip-safe
distributions_package_oop.egg-info/top_level.txt