Metadata-Version: 1.0
Name: distributions-package-oop
Version: 0.1
Summary: Gaussian and Binomial distributions
Home-page: UNKNOWN
Author: Paul Owoicho
Author-email: paulowoicho@gmail.com
License: UNKNOWN
Platform: UNKNOWN
